deeptracktorch/__init__.py
deeptracktorch/_nbdev.py
deeptracktorch/cli.py
deeptracktorch/model.py
deeptracktorch/models.py
deeptracktorch/simg.py
deeptracktorch-0.0.1.dist-info/LICENSE
deeptracktorch-0.0.1.dist-info/METADATA
deeptracktorch-0.0.1.dist-info/WHEEL
deeptracktorch-0.0.1.dist-info/entry_points.txt
deeptracktorch-0.0.1.dist-info/top_level.txt
deeptracktorch-0.0.1.dist-info/RECORD
