Metadata-Version: 2.1
Name: deeptracktorch
Version: 0.0.1
Summary: PyTorch clone of DeepTrack
Home-page: https://github.com/wooduk/deeptracktorch
Author: Stephen Wood
Author-email: sgwooduk@gmail.com
License: Apache Software License 2.0
Keywords: deeplearning torch
Platform: UNKNOWN
Classifier: Development Status :: 3 - Alpha
Classifier: Intended Audience :: Developers
Classifier: License :: OSI Approved :: Apache Software License
Classifier: Natural Language :: English
Classifier: Programming Language :: Python :: 3.8
Requires-Python: >=3.8
